setup.py
change_font_size/__init__.py
change_font_size/change_font.py
change_font_size.egg-info/PKG-INFO
change_font_size.egg-info/SOURCES.txt
change_font_size.egg-info/dependency_links.txt
change_font_size.egg-info/top_level.txt